pymultidispatch/__init__.py
pymultidispatch/multimethods.py
pymultidispatch-1.2.0.dist-info/LICENSE
pymultidispatch-1.2.0.dist-info/METADATA
pymultidispatch-1.2.0.dist-info/WHEEL
pymultidispatch-1.2.0.dist-info/top_level.txt
pymultidispatch-1.2.0.dist-info/RECORD
