Metadata-Version: 2.1
Name: pymultidispatch
Version: 1.2.0
Summary: Multimethods implementation in Python
Home-page: https://github.com/purefunctions/pymultidispatch/
Author: Siva Jayaraman
Author-email: purefunctions.os@outlook.com
License: UNKNOWN
Platform: UNKNOWN
Classifier: Programming Language :: Python :: 3.6
Classifier: Programming Language :: Python :: 3.7
Classifier: Programming Language :: Python :: 3.8
Classifier: Programming Language :: Python :: 3.9
Classifier: License :: OSI Approved :: MIT License
License-File: LICENSE
